agent.py
llms/__init__.py
llms/api_llm.py
llms/api_llm_integration_test.py
llms/api_llm_unit_test.py
llms/llm.py
llms/llm_unit_test.py
tools/__init__.py
tools/base_tool.py
tools/base_tool_unit_test.py
tools/console_tool.py
tools/console_tool_integration_test.py
tools/console_tool_unit_test.py
pc_agent-0.5.10.dist-info/METADATA
pc_agent-0.5.10.dist-info/WHEEL
pc_agent-0.5.10.dist-info/top_level.txt
pc_agent-0.5.10.dist-info/RECORD
